enot_lite-0.8.1.dist-info/RECORD
enot_lite-0.8.1.dist-info/METADATA
enot_lite-0.8.1.dist-info/top_level.txt
enot_lite-0.8.1.dist-info/LICENSE
enot_lite-0.8.1.dist-info/WHEEL
enot_lite/__init__.py
enot_lite/VERSION
enot_lite/type/__init__.py
enot_lite/type/interface.cpython-38-x86_64-linux-gnu.so
enot_lite/benchmark/backend_runner.py
enot_lite/benchmark/__init__.py
enot_lite/benchmark/backend_benchmark.py
enot_lite/benchmark/backend_runner_factory.py
enot_lite/benchmark/benchmark.py
enot_lite/benchmark/utils.py
enot_lite/benchmark/backend_runner_builder.py
enot_lite/calibration/__init__.py
enot_lite/calibration/calibrator_ort.cpython-38-x86_64-linux-gnu.so
enot_lite/calibration/calibration_table_tensorrt.cpython-38-x86_64-linux-gnu.so
enot_lite/optimizer/input_model_optimizer.cpython-38-x86_64-linux-gnu.so
enot_lite/optimizer/optimizer_factory.cpython-38-x86_64-linux-gnu.so
enot_lite/optimizer/__init__.py
enot_lite/optimizer/fp16_model_optimizer.cpython-38-x86_64-linux-gnu.so
enot_lite/optimizer/optimizer_builder.cpython-38-x86_64-linux-gnu.so
enot_lite/optimizer/model_optimizer.cpython-38-x86_64-linux-gnu.so
enot_lite/optimizer/tensorrt_nms_optimizer.cpython-38-x86_64-linux-gnu.so
enot_lite/optimizer/common.cpython-38-x86_64-linux-gnu.so
enot_lite/optimizer/general_model_optimizer.cpython-38-x86_64-linux-gnu.so
enot_lite/optimizer/dead_node_optimizer.cpython-38-x86_64-linux-gnu.so
enot_lite/optimizer/models/__init__.py
enot_lite/optimizer/models/registry.cpython-38-x86_64-linux-gnu.so
enot_lite/optimizer/models/yolo.cpython-38-x86_64-linux-gnu.so
enot_lite/backend/ort_cuda.cpython-38-x86_64-linux-gnu.so
enot_lite/backend/__init__.py
enot_lite/backend/openvino.cpython-38-x86_64-linux-gnu.so
enot_lite/backend/backend.cpython-38-x86_64-linux-gnu.so
enot_lite/backend/ort_tensorrt.cpython-38-x86_64-linux-gnu.so
enot_lite/backend/tensorrt.cpython-38-x86_64-linux-gnu.so
enot_lite/backend/backend_factory.cpython-38-x86_64-linux-gnu.so
enot_lite/backend/backend_builder.cpython-38-x86_64-linux-gnu.so
enot_lite/backend/ort_openvino.cpython-38-x86_64-linux-gnu.so
