Metadata-Version: 2.1
Name: enot-lite
Version: 0.8.1
Summary: UNKNOWN
Home-page: https://enot.ai
Author: ENOT LLC
Author-email: enot@enot.ai
License: ENOT License v1.0
Keywords: AI,Neural architecture search
Platform: UNKNOWN
Classifier: License :: Other/Proprietary License
License-File: LICENSE
Requires-Dist: onnx
Requires-Dist: onnx-simplifier (==0.3.8)
Requires-Dist: tabulate
